rpi_mini_battery_display/__init__.py
rpi_mini_battery_display/__main__.py
rpi_mini_battery_display/exceptions.py
rpi_mini_battery_display-0.3.0.data/scripts/rpi-mini-battery-display
rpi_mini_battery_display-0.3.0.dist-info/LICENSE
rpi_mini_battery_display-0.3.0.dist-info/METADATA
rpi_mini_battery_display-0.3.0.dist-info/WHEEL
rpi_mini_battery_display-0.3.0.dist-info/top_level.txt
rpi_mini_battery_display-0.3.0.dist-info/RECORD
