Metadata-Version: 2.1
Name: rpi-mini-battery-display
Version: 0.3.0
Summary: Control 10-segment mini battery displays on a Raspberry Pi
Home-page: https://github.com/koenvervloesem/rpi-mini-battery-display
Author: Koen Vervloesem
Author-email: koen@vervloesem.eu
License: MIT
Project-URL: Documentation, https://github.com/koenvervloesem/rpi-mini-battery-display
Project-URL: Source, https://github.com/koenvervloesem/rpi-mini-battery-display
Project-URL: Tracker, https://github.com/koenvervloesem/rpi-mini-battery-display/issues
Keywords: tm1651,raspberry-pi,rpi,rpi-gpio,display,gpio,led
Platform: UNKNOWN
Classifier: Development Status :: 5 - Production/Stable
Classifier: Environment :: Console
Classifier: Operating System :: POSIX :: Linux
Classifier: Programming Language :: Python :: 3
Classifier: Programming Language :: Python :: 3.6
Classifier: Programming Language :: Python :: 3.7
Classifier: Programming Language :: Python :: 3.8
Classifier: License :: OSI Approved :: MIT License
Requires-Python: >=3
Requires-Dist: RPi.GPIO
Requires-Dist: psutil
